{
  "text": " Hello and welcome to my therapist plays disco elicium analysis series. So on today's episode I'm very excited because we are finally getting to use one of my absolute favorite frameworks for analyzing characters. This is something that I use in therapy from time to time and it's an incredible way to explore patterns of psychology and patterns of behavior and sort of really uncover what is driving a lot of the complexes that we see play out in Harry's thoughts and his actions. And the reason we were doing that now is because we are starting to learn more about ourselves and our past. We're going to take another look at that ledger and see what do we actually think about the person that we used to be before we became a sorry cop. All that's coming up so let's jump back in. Oh there it is. There it is. We are back. We are so back. I'm so excited. Okay so we are back in the game now. I just wanted to say the community that has arrived around like this game and specifically this playthrough continues to amaze me especially after last episode was like a lot of politics talk and I was very like anxious avoidant of talking about politics. I have been very encouraged by the response to that last episode to like not be so anxious about it. I don't I still don't know if I'm gonna like start getting full political but I will try not to like avoid it in the game because of my personal issues with with getting political. I'll just say that I I won't let it divert the game because at the end of the day I want to talk about like mental health and there's probably some interesting avenues in the narrative of the game that will miss out on if I just totally ignore it. However I will say this game is so wonderfully designed that it you have a main character who has a real back story. He's not like a blank slate like I thought that he was gonna be from the beginning. He has his own back story and at the same time it allows you to have your own beliefs and and to and the character will like have the same behavioral patterns. Like genuinely imagine if like literally Brady was the detective. Imagine it what you know about me so far. How I would go about solving a murder would be exactly like you've seen it like I would spend crazy amounts of time on things that you just wouldn't like you.",
  "segments": [
    {
      "id": 0,
      "seek": 0,
      "start": 0.68,
      "end": 6.1,
      "text": " Hello and welcome to my therapist plays disco elicium analysis series. So on",
      "tokens": [
        2425,
        293,
        2928,
        281,
        452,
        19830,
        5749,
        3622,
        806,
        299,
        2197,
        5215,
        2638,
        13,
        407,
        322
      ],
      "temperature": 0.0,
      "avg_logprob": -0.1728581605955612,
      "compression_ratio": 1.6024590163934427,
      "no_speech_prob": 0.21501588821411133,
      "confidence": 0.719,
      "words": [
        {
          "text": "Hello",
          "start": 0.68,
          "end": 0.9,
          "confidence": 0.903
        },
        {
          "text": "and",
          "start": 0.9,
          "end": 1.62,
          "confidence": 0.533
        },
        {
          "text": "welcome",
          "start": 1.62,
          "end": 1.84,
          "confidence": 0.993
        },
        {
          "text": "to",
          "start": 1.84,
          "end": 2.16,
          "confidence": 0.998
        },
        {
          "text": "my",
          "start": 2.16,
          "end": 2.54,
          "confidence": 0.981
        },
        {
          "text": "therapist",
          "start": 2.54,
          "end": 3.04,
          "confidence": 0.836
        },
        {
          "text": "plays",
          "start": 3.04,
          "end": 3.46,
          "confidence": 0.879
        },
        {
          "text": "disco",
          "start": 3.46,
          "end": 3.84,
          "confidence": 0.605
        },
        {
          "text": "elicium",
          "start": 3.84,
          "end": 4.34,
          "confidence": 0.448
        },
        {
          "text": "analysis",
          "start": 4.34,
          "end": 4.78,
          "confidence": 0.909
        },
        {
          "text": "series.",
          "start": 4.78,
          "end": 5.2,
          "confidence": 0.983
        },
        {
          "text": "So",
          "start": 5.7,
          "end": 5.84,
          "confidence": 0.5
        },
        {
          "text": "on",
          "start": 5.84,
          "end": 6.1,
          "confidence": 0.846
        }
      ]
    },
    {
      "id": 1,
      "seek": 0,
      "start": 6.1,
      "end": 10.54,
      "text": " today's episode I'm very excited because we are finally getting to use one of my",
      "tokens": [
        965,
        311,
        3500,
        286,
        478,
        588,
        2919,
        570,
        321,
        366,
        2721,
        1242,
        281,
        764,
        472,
        295,
        452
      ],
      "temperature": 0.0,
      "avg_logprob": -0.1728581605955612,
      "compression_ratio": 1.6024590163934427,
      "no_speech_prob": 0.21501588821411133,
      "confidence": 0.922,
      "words": [
        {
          "text": "today's",
          "start": 6.1,
          "end": 6.44,
          "confidence": 0.995
        },
        {
          "text": "episode",
          "start": 6.44,
          "end": 6.72,
          "confidence": 0.998
        },
        {
          "text": "I'm",
          "start": 6.72,
          "end": 7.18,
          "confidence": 0.83
        },
        {
          "text": "very",
          "start": 7.18,
          "end": 7.36,
          "confidence": 0.999
        },
        {
          "text": "excited",
          "start": 7.36,
          "end": 7.82,
          "confidence": 0.999
        },
        {
          "text": "because",
          "start": 7.82,
          "end": 8.5,
          "confidence": 0.953
        },
        {
          "text": "we",
          "start": 8.5,
          "end": 8.98,
          "confidence": 0.998
        },
        {
          "text": "are",
          "start": 8.98,
          "end": 9.1,
          "confidence": 0.988
        },
        {
          "text": "finally",
          "start": 9.1,
          "end": 9.3,
          "confidence": 0.997
        },
        {
          "text": "getting",
          "start": 9.3,
          "end": 9.52,
          "confidence": 0.994
        },
        {
          "text": "to",
          "start": 9.52,
          "end": 9.72,
          "confidence": 0.998
        },
        {
          "text": "use",
          "start": 9.72,
          "end": 9.92,
          "confidence": 0.987
        },
        {
          "text": "one",
          "start": 9.92,
          "end": 10.2,
          "confidence": 0.919
        },
        {
          "text": "of",
          "start": 10.2,
          "end": 10.32,
          "confidence": 0.884
        },
        {
          "text": "my",
          "start": 10.32,
          "end": 10.54,
          "confidence": 0.5
        }
      ]
    },
    {
      "id": 2,
      "seek": 0,
      "start": 10.54,
      "end": 15.8,
      "text": " absolute favorite frameworks for analyzing characters. This is something that I",
      "tokens": [
        8236,
        2954,
        29834,
        337,
        23663,
        4342,
        13,
        639,
        307,
        746,
        300,
        286
      ],
      "temperature": 0.0,
      "avg_logprob": -0.1728581605955612,
      "compression_ratio": 1.6024590163934427,
      "no_speech_prob": 0.21501588821411133,
      "confidence": 0.967,
      "words": [
        {
          "text": "absolute",
          "start": 10.54,
          "end": 11.22,
          "confidence": 0.996
        },
        {
          "text": "favorite",
          "start": 11.22,
          "end": 12.18,
          "confidence": 0.967
        },
        {
          "text": "frameworks",
          "start": 12.18,
          "end": 12.76,
          "confidence": 0.949
        },
        {
          "text": "for",
          "start": 12.76,
          "end": 13.26,
          "confidence": 0.999
        },
        {
          "text": "analyzing",
          "start": 13.26,
          "end": 13.94,
          "confidence": 0.973
        },
        {
          "text": "characters.",
          "start": 13.94,
          "end": 14.56,
          "confidence": 0.972
        },
        {
          "text": "This",
          "start": 15.1,
          "end": 15.28,
          "confidence": 0.955
        },
        {
          "text": "is",
          "start": 15.28,
          "end": 15.38,
          "confidence": 0.998
        },
        {
          "text": "something",
          "start": 15.38,
          "end": 15.56,
          "confidence": 0.992
        },
        {
          "text": "that",
          "start": 15.56,
          "end": 15.72,
          "confidence": 0.89
        },
        {
          "text": "I",
          "start": 15.72,
          "end": 15.8,
          "confidence": 0.951
        }
      ]
    },
    {
      "id": 3,
      "seek": 0,
      "start": 15.8,
      "end": 22.38,
      "text": " use in therapy from time to time and it's an incredible way to explore patterns",
      "tokens": [
        764,
        294,
        9492,
        490,
        565,
        281,
        565,
        293,
        309,
        311,
        364,
        4651,
        636,
        281,
        6839,
        8294
      ],
      "temperature": 0.0,
      "avg_logprob": -0.1728581605955612,
      "compression_ratio": 1.6024590163934427,
      "no_speech_prob": 0.21501588821411133,
      "confidence": 0.967,
      "words": [
        {
          "text": "use",
          "start": 15.8,
          "end": 16.04,
          "confidence": 0.987
        },
        {
          "text": "in",
          "start": 16.04,
          "end": 16.28,
          "confidence": 0.995
        },
        {
          "text": "therapy",
          "start": 16.28,
          "end": 16.58,
          "confidence": 0.997
        },
        {
          "text": "from",
          "start": 16.58,
          "end": 16.86,
          "confidence": 0.993
        },
        {
          "text": "time",
          "start": 16.86,
          "end": 17.06,
          "confidence": 0.999
        },
        {
          "text": "to",
          "start": 17.06,
          "end": 17.22,
          "confidence": 0.991
        },
        {
          "text": "time",
          "start": 17.22,
          "end": 17.46,
          "confidence": 1.0
        },
        {
          "text": "and",
          "start": 17.46,
          "end": 17.72,
          "confidence": 0.844
        },
        {
          "text": "it's",
          "start": 17.72,
          "end": 18.14,
          "confidence": 0.995
        },
        {
          "text": "an",
          "start": 18.14,
          "end": 18.88,
          "confidence": 0.996
        },
        {
          "text": "incredible",
          "start": 18.88,
          "end": 19.44,
          "confidence": 0.985
        },
        {
          "text": "way",
          "start": 19.44,
          "end": 20.52,
          "confidence": 0.986
        },
        {
          "text": "to",
          "start": 20.52,
          "end": 20.98,
          "confidence": 0.998
        },
        {
          "text": "explore",
          "start": 20.98,
          "end": 21.82,
          "confidence": 0.966
        },
        {
          "text": "patterns",
          "start": 21.82,
          "end": 22.38,
          "confidence": 0.774
        }
      ]
    },
    {
      "id": 4,
      "seek": 0,
      "start": 22.48,
      "end": 26.56,
      "text": " of psychology and patterns of behavior and sort of really uncover what is",
      "tokens": [
        295,
        15105,
        293,
        8294,
        295,
        5223,
        293,
        1333,
        295,
        534,
        21694,
        437,
        307
      ],
      "temperature": 0.0,
      "avg_logprob": -0.1728581605955612,
      "compression_ratio": 1.6024590163934427,
      "no_speech_prob": 0.21501588821411133,
      "confidence": 0.985,
      "words": [
        {
          "text": "of",
          "start": 22.48,
          "end": 22.64,
          "confidence": 0.999
        },
        {
          "text": "psychology",
          "start": 22.64,
          "end": 23.1,
          "confidence": 0.997
        },
        {
          "text": "and",
          "start": 23.1,
          "end": 23.34,
          "confidence": 0.938
        },
        {
          "text": "patterns",
          "start": 23.34,
          "end": 23.6,
          "confidence": 0.994
        },
        {
          "text": "of",
          "start": 23.6,
          "end": 23.78,
          "confidence": 0.997
        },
        {
          "text": "behavior",
          "start": 23.78,
          "end": 24.14,
          "confidence": 0.969
        },
        {
          "text": "and",
          "start": 24.14,
          "end": 24.46,
          "confidence": 0.951
        },
        {
          "text": "sort",
          "start": 24.46,
          "end": 24.64,
          "confidence": 0.991
        },
        {
          "text": "of",
          "start": 24.64,
          "end": 24.8,
          "confidence": 0.999
        },
        {
          "text": "really",
          "start": 24.8,
          "end": 25.54,
          "confidence": 0.99
        },
        {
          "text": "uncover",
          "start": 25.54,
          "end": 25.98,
          "confidence": 0.997
        },
        {
          "text": "what",
          "start": 25.98,
          "end": 26.4,
          "confidence": 0.989
        },
        {
          "text": "is",
          "start": 26.4,
          "end": 26.56,
          "confidence": 0.99
        }
      ]
    },
    {
      "id": 5,
      "seek": 2660,
      "start": 26.6,
      "end": 33.66,
      "text": " driving a lot of the complexes that we see play out in Harry's thoughts and his",
      "tokens": [
        4840,
        257,
        688,
        295,
        264,
        43676,
        300,
        321,
        536,
        862,
        484,
        294,
        9378,
        311,
        4598,
        293,
        702
      ],
      "temperature": 0.0,
      "avg_logprob": -0.15964169404944595,
      "compression_ratio": 1.634453781512605,
      "no_speech_prob": 0.0001569089654367417,
      "confidence": 0.937,
      "words": [
        {
          "text": "driving",
          "start": 26.6,
          "end": 27.14,
          "confidence": 0.998
        },
        {
          "text": "a",
          "start": 27.14,
          "end": 27.46,
          "confidence": 0.997
        },
        {
          "text": "lot",
          "start": 27.46,
          "end": 27.76,
          "confidence": 1.0
        },
        {
          "text": "of",
          "start": 27.76,
          "end": 28.02,
          "confidence": 1.0
        },
        {
          "text": "the",
          "start": 28.02,
          "end": 28.18,
          "confidence": 0.999
        },
        {
          "text": "complexes",
          "start": 28.18,
          "end": 28.76,
          "confidence": 0.995
        },
        {
          "text": "that",
          "start": 28.76,
          "end": 29.08,
          "confidence": 0.997
        },
        {
          "text": "we",
          "start": 29.08,
          "end": 29.22,
          "confidence": 1.0
        },
        {
          "text": "see",
          "start": 29.22,
          "end": 29.46,
          "confidence": 0.999
        },
        {
          "text": "play",
          "start": 29.46,
          "end": 29.76,
          "confidence": 0.989
        },
        {
          "text": "out",
          "start": 29.76,
          "end": 30.06,
          "confidence": 0.995
        },
        {
          "text": "in",
          "start": 30.06,
          "end": 30.66,
          "confidence": 0.994
        },
        {
          "text": "Harry's",
          "start": 30.66,
          "end": 32.42,
          "confidence": 0.839
        },
        {
          "text": "thoughts",
          "start": 32.42,
          "end": 32.64,
          "confidence": 0.949
        },
        {
          "text": "and",
          "start": 32.64,
          "end": 33.28,
          "confidence": 0.939
        },
        {
          "text": "his",
          "start": 33.28,
          "end": 33.66,
          "confidence": 0.548
        }
      ]
    },
    {
      "id": 6,
      "seek": 2660,
      "start": 33.66,
      "end": 38.38,
      "text": " actions. And the reason we were doing that now is because we are starting to",
      "tokens": [
        5909,
        13,
        400,
        264,
        1778,
        321,
        645,
        884,
        300,
        586,
        307,
        570,
        321,
        366,
        2891,
        281
      ],
      "temperature": 0.0,
      "avg_logprob": -0.15964169404944595,
      "compression_ratio": 1.634453781512605,
      "no_speech_prob": 0.0001569089654367417,
      "confidence": 0.937,
      "words": [
        {
          "text": "actions.",
          "start": 33.66,
          "end": 34.16,
          "confidence": 0.999
        },
        {
          "text": "And",
          "start": 34.74,
          "end": 34.86,
          "confidence": 0.903
        },
        {
          "text": "the",
          "start": 34.86,
          "end": 34.94,
          "confidence": 0.998
        },
        {
          "text": "reason",
          "start": 34.94,
          "end": 35.16,
          "confidence": 0.999
        },
        {
          "text": "we",
          "start": 35.16,
          "end": 35.32,
          "confidence": 0.999
        },
        {
          "text": "were",
          "start": 35.32,
          "end": 35.42,
          "confidence": 0.578
        },
        {
          "text": "doing",
          "start": 35.42,
          "end": 35.62,
          "confidence": 0.999
        },
        {
          "text": "that",
          "start": 35.62,
          "end": 35.8,
          "confidence": 0.999
        },
        {
          "text": "now",
          "start": 35.8,
          "end": 36.14,
          "confidence": 0.997
        },
        {
          "text": "is",
          "start": 36.14,
          "end": 36.4,
          "confidence": 0.99
        },
        {
          "text": "because",
          "start": 36.4,
          "end": 36.7,
          "confidence": 0.983
        },
        {
          "text": "we",
          "start": 36.7,
          "end": 37.56,
          "confidence": 0.995
        },
        {
          "text": "are",
          "start": 37.56,
          "end": 37.7,
          "confidence": 0.844
        },
        {
          "text": "starting",
          "start": 37.7,
          "end": 38.16,
          "confidence": 0.984
        },
        {
          "text": "to",
          "start": 38.16,
          "end": 38.38,
          "confidence": 0.911
        }
      ]
    },
    {
      "id": 7,
      "seek": 2660,
      "start": 38.38,
      "end": 42.13,
      "text": " learn more about ourselves and our past. We're going to take another look at",
      "tokens": [
        1466,
        544,
        466,
        4175,
        293,
        527,
        1791,
        13,
        492,
        434,
        516,
        281,
        747,
        1071,
        574,
        412
      ],
      "temperature": 0.0,
      "avg_logprob": -0.15964169404944595,
      "compression_ratio": 1.634453781512605,
      "no_speech_prob": 0.0001569089654367417,
      "confidence": 0.902,
      "words": [
        {
          "text": "learn",
          "start": 38.38,
          "end": 38.6,
          "confidence": 0.999
        },
        {
          "text": "more",
          "start": 38.6,
          "end": 38.82,
          "confidence": 0.999
        },
        {
          "text": "about",
          "start": 38.82,
          "end": 39.04,
          "confidence": 1.0
        },
        {
          "text": "ourselves",
          "start": 39.04,
          "end": 39.46,
          "confidence": 0.998
        },
        {
          "text": "and",
          "start": 39.46,
          "end": 39.88,
          "confidence": 0.768
        },
        {
          "text": "our",
          "start": 39.88,
          "end": 40.0,
          "confidence": 0.997
        },
        {
          "text": "past.",
          "start": 40.0,
          "end": 40.46,
          "confidence": 0.999
        },
        {
          "text": "We're",
          "start": 40.94,
          "end": 41.14,
          "confidence": 0.838
        },
        {
          "text": "going",
          "start": 41.14,
          "end": 41.2,
          "confidence": 0.449
        },
        {
          "text": "to",
          "start": 41.2,
          "end": 41.26,
          "confidence": 0.993
        },
        {
          "text": "take",
          "start": 41.26,
          "end": 41.36,
          "confidence": 0.997
        },
        {
          "text": "another",
          "start": 41.36,
          "end": 41.56,
          "confidence": 0.989
        },
        {
          "text": "look",
          "start": 41.56,
          "end": 41.78,
          "confidence": 0.978
        },
        {
          "text": "at",
          "start": 41.78,
          "end": 42.13,
          "confidence": 0.925
        }
      ]
    },
    {
      "id": 8,
      "seek": 2660,
      "start": 42.13,
      "end": 46.58,
      "text": " that ledger and see what do we actually think about the person that we used to",
      "tokens": [
        300,
        4684,
        1321,
        293,
        536,
        437,
        360,
        321,
        767,
        519,
        466,
        264,
        954,
        300,
        321,
        1143,
        281
      ],
      "temperature": 0.0,
      "avg_logprob": -0.15964169404944595,
      "compression_ratio": 1.634453781512605,
      "no_speech_prob": 0.0001569089654367417,
      "confidence": 0.965,
      "words": [
        {
          "text": "that",
          "start": 42.13,
          "end": 42.32,
          "confidence": 0.998
        },
        {
          "text": "ledger",
          "start": 42.32,
          "end": 42.74,
          "confidence": 0.994
        },
        {
          "text": "and",
          "start": 42.74,
          "end": 43.04,
          "confidence": 0.995
        },
        {
          "text": "see",
          "start": 43.04,
          "end": 43.38,
          "confidence": 0.999
        },
        {
          "text": "what",
          "start": 43.38,
          "end": 44.54,
          "confidence": 0.864
        },
        {
          "text": "do",
          "start": 44.54,
          "end": 44.62,
          "confidence": 0.956
        },
        {
          "text": "we",
          "start": 44.62,
          "end": 44.74,
          "confidence": 0.999
        },
        {
          "text": "actually",
          "start": 44.74,
          "end": 45.08,
          "confidence": 0.997
        },
        {
          "text": "think",
          "start": 45.08,
          "end": 45.36,
          "confidence": 0.999
        },
        {
          "text": "about",
          "start": 45.36,
          "end": 45.56,
          "confidence": 0.992
        },
        {
          "text": "the",
          "start": 45.56,
          "end": 45.7,
          "confidence": 0.992
        },
        {
          "text": "person",
          "start": 45.7,
          "end": 46.0,
          "confidence": 0.994
        },
        {
          "text": "that",
          "start": 46.0,
          "end": 46.18,
          "confidence": 0.988
        },
        {
          "text": "we",
          "start": 46.18,
          "end": 46.32,
          "confidence": 0.977
        },
        {
          "text": "used",
          "start": 46.32,
          "end": 46.46,
          "confidence": 0.877
        },
        {
          "text": "to",
          "start": 46.46,
          "end": 46.58,
          "confidence": 0.82
        }
      ]
    },
    {
      "id": 9,
      "seek": 2660,
      "start": 46.58,
      "end": 52.02,
      "text": " be before we became a sorry cop. All that's coming up so let's jump back in.",
      "tokens": [
        312,
        949,
        321,
        3062,
        257,
        2597,
        2971,
        13,
        1057,
        300,
        311,
        1348,
        493,
        370,
        718,
        311,
        3012,
        646,
        294,
        13
      ],
      "temperature": 0.0,
      "avg_logprob": -0.15964169404944595,
      "compression_ratio": 1.634453781512605,
      "no_speech_prob": 0.0001569089654367417,
      "confidence": 0.932,
      "words": [
        {
          "text": "be",
          "start": 46.58,
          "end": 46.82,
          "confidence": 0.999
        },
        {
          "text": "before",
          "start": 46.82,
          "end": 47.88,
          "confidence": 0.914
        },
        {
          "text": "we",
          "start": 47.88,
          "end": 48.08,
          "confidence": 0.998
        },
        {
          "text": "became",
          "start": 48.08,
          "end": 48.36,
          "confidence": 0.992
        },
        {
          "text": "a",
          "start": 48.36,
          "end": 48.52,
          "confidence": 0.924
        },
        {
          "text": "sorry",
          "start": 48.52,
          "end": 48.7,
          "confidence": 0.92
        },
        {
          "text": "cop.",
          "start": 48.7,
          "end": 48.98,
          "confidence": 0.988
        },
        {
          "text": "All",
          "start": 49.56,
          "end": 49.84,
          "confidence": 0.795
        },
        {
          "text": "that's",
          "start": 49.84,
          "end": 50.04,
          "confidence": 0.997
        },
        {
          "text": "coming",
          "start": 50.04,
          "end": 50.18,
          "confidence": 0.986
        },
        {
          "text": "up",
          "start": 50.18,
          "end": 50.34,
          "confidence": 0.999
        },
        {
          "text": "so",
          "start": 50.34,
          "end": 50.74,
          "confidence": 0.7
        },
        {
          "text": "let's",
          "start": 50.74,
          "end": 51.48,
          "confidence": 0.933
        },
        {
          "text": "jump",
          "start": 51.48,
          "end": 51.62,
          "confidence": 0.985
        },
        {
          "text": "back",
          "start": 51.62,
          "end": 51.8,
          "confidence": 0.882
        },
        {
          "text": "in.",
          "start": 51.8,
          "end": 52.02,
          "confidence": 0.894
        }
      ]
    },
    {
      "id": 10,
      "seek": 5276,
      "start": 52.84,
      "end": 64.44,
      "text": " Oh there it is. There it is. We are back. We are so back. I'm so excited. Okay so we",
      "tokens": [
        876,
        456,
        309,
        307,
        13,
        821,
        309,
        307,
        13,
        492,
        366,
        646,
        13,
        492,
        366,
        370,
        646,
        13,
        286,
        478,
        370,
        2919,
        13,
        1033,
        370,
        321
      ],
      "temperature": 0.0,
      "avg_logprob": -0.21075425382520332,
      "compression_ratio": 1.5503355704697988,
      "no_speech_prob": 0.00017132323409896344,
      "confidence": 0.784,
      "words": [
        {
          "text": "Oh",
          "start": 52.84,
          "end": 53.26,
          "confidence": 0.651
        },
        {
          "text": "there",
          "start": 53.26,
          "end": 53.94,
          "confidence": 0.479
        },
        {
          "text": "it",
          "start": 53.94,
          "end": 54.04,
          "confidence": 0.992
        },
        {
          "text": "is.",
          "start": 54.04,
          "end": 54.26,
          "confidence": 0.998
        },
        {
          "text": "There",
          "start": 55.1,
          "end": 55.42,
          "confidence": 0.988
        },
        {
          "text": "it",
          "start": 55.42,
          "end": 55.56,
          "confidence": 0.996
        },
        {
          "text": "is.",
          "start": 55.56,
          "end": 55.94,
          "confidence": 0.999
        },
        {
          "text": "We",
          "start": 56.22,
          "end": 56.42,
          "confidence": 0.99
        },
        {
          "text": "are",
          "start": 56.42,
          "end": 56.52,
          "confidence": 0.75
        },
        {
          "text": "back.",
          "start": 56.52,
          "end": 56.76,
          "confidence": 0.996
        },
        {
          "text": "We",
          "start": 57.2,
          "end": 57.5,
          "confidence": 0.951
        },
        {
          "text": "are",
          "start": 57.5,
          "end": 57.58,
          "confidence": 0.538
        },
        {
          "text": "so",
          "start": 57.58,
          "end": 57.82,
          "confidence": 0.984
        },
        {
          "text": "back.",
          "start": 57.82,
          "end": 58.18,
          "confidence": 0.974
        },
        {
          "text": "I'm",
          "start": 58.56,
          "end": 61.54,
          "confidence": 0.552
        },
        {
          "text": "so",
          "start": 61.54,
          "end": 61.68,
          "confidence": 0.967
        },
        {
          "text": "excited.",
          "start": 61.68,
          "end": 62.0,
          "confidence": 0.986
        },
        {
          "text": "Okay",
          "start": 63.28,
          "end": 63.64,
          "confidence": 0.669
        },
        {
          "text": "so",
          "start": 63.64,
          "end": 64.14,
          "confidence": 0.505
        },
        {
          "text": "we",
          "start": 64.14,
          "end": 64.44,
          "confidence": 0.562
        }
      ]
    },
    {
      "id": 11,
      "seek": 5276,
      "start": 64.44,
      "end": 73.04,
      "text": " are back in the game now. I just wanted to say the community that has arrived",
      "tokens": [
        366,
        646,
        294,
        264,
        1216,
        586,
        13,
        286,
        445,
        1415,
        281,
        584,
        264,
        1768,
        300,
        575,
        6678
      ],
      "temperature": 0.0,
      "avg_logprob": -0.21075425382520332,
      "compression_ratio": 1.5503355704697988,
      "no_speech_prob": 0.00017132323409896344,
      "confidence": 0.947,
      "words": [
        {
          "text": "are",
          "start": 64.44,
          "end": 64.6,
          "confidence": 0.999
        },
        {
          "text": "back",
          "start": 64.6,
          "end": 64.9,
          "confidence": 0.997
        },
        {
          "text": "in",
          "start": 64.9,
          "end": 66.02,
          "confidence": 0.978
        },
        {
          "text": "the",
          "start": 66.02,
          "end": 66.12,
          "confidence": 0.998
        },
        {
          "text": "game",
          "start": 66.12,
          "end": 66.28,
          "confidence": 0.999
        },
        {
          "text": "now.",
          "start": 66.28,
          "end": 66.5,
          "confidence": 0.98
        },
        {
          "text": "I",
          "start": 66.84,
          "end": 67.22,
          "confidence": 0.994
        },
        {
          "text": "just",
          "start": 67.22,
          "end": 67.32,
          "confidence": 0.999
        },
        {
          "text": "wanted",
          "start": 67.32,
          "end": 67.52,
          "confidence": 0.992
        },
        {
          "text": "to",
          "start": 67.52,
          "end": 67.68,
          "confidence": 0.999
        },
        {
          "text": "say",
          "start": 67.68,
          "end": 67.98,
          "confidence": 0.997
        },
        {
          "text": "the",
          "start": 67.98,
          "end": 69.44,
          "confidence": 0.611
        },
        {
          "text": "community",
          "start": 69.44,
          "end": 71.54,
          "confidence": 0.968
        },
        {
          "text": "that",
          "start": 71.54,
          "end": 72.04,
          "confidence": 0.988
        },
        {
          "text": "has",
          "start": 72.04,
          "end": 72.54,
          "confidence": 0.986
        },
        {
          "text": "arrived",
          "start": 72.54,
          "end": 73.04,
          "confidence": 0.778
        }
      ]
    },
    {
      "id": 12,
      "seek": 5276,
      "start": 73.3,
      "end": 78.41,
      "text": " around like this game and specifically this playthrough continues to",
      "tokens": [
        926,
        411,
        341,
        1216,
        293,
        4682,
        341,
        48752,
        6515,
        281
      ],
      "temperature": 0.0,
      "avg_logprob": -0.21075425382520332,
      "compression_ratio": 1.5503355704697988,
      "no_speech_prob": 0.00017132323409896344,
      "confidence": 0.967,
      "words": [
        {
          "text": "around",
          "start": 73.3,
          "end": 73.88,
          "confidence": 0.999
        },
        {
          "text": "like",
          "start": 73.88,
          "end": 74.22,
          "confidence": 0.964
        },
        {
          "text": "this",
          "start": 74.22,
          "end": 75.06,
          "confidence": 0.986
        },
        {
          "text": "game",
          "start": 75.06,
          "end": 75.28,
          "confidence": 0.999
        },
        {
          "text": "and",
          "start": 75.28,
          "end": 75.5,
          "confidence": 0.94
        },
        {
          "text": "specifically",
          "start": 75.5,
          "end": 76.02,
          "confidence": 0.996
        },
        {
          "text": "this",
          "start": 76.02,
          "end": 76.3,
          "confidence": 0.98
        },
        {
          "text": "playthrough",
          "start": 76.3,
          "end": 76.74,
          "confidence": 0.894
        },
        {
          "text": "continues",
          "start": 76.74,
          "end": 78.2,
          "confidence": 0.932
        },
        {
          "text": "to",
          "start": 78.2,
          "end": 78.41,
          "confidence": 0.986
        }
      ]
    },
    {
      "id": 13,
      "seek": 7840,
      "start": 78.41,
      "end": 83.22,
      "text": " amaze me especially after last episode was like a lot of politics talk and I was",
      "tokens": [
        669,
        13660,
        385,
        2318,
        934,
        1036,
        3500,
        390,
        411,
        257,
        688,
        295,
        7341,
        751,
        293,
        286,
        390
      ],
      "temperature": 0.0,
      "avg_logprob": -0.16343972590062525,
      "compression_ratio": 1.675531914893617,
      "no_speech_prob": 0.0002010688913287595,
      "confidence": 0.888,
      "words": [
        {
          "text": "amaze",
          "start": 78.41,
          "end": 78.68,
          "confidence": 0.975
        },
        {
          "text": "me",
          "start": 78.68,
          "end": 78.92,
          "confidence": 0.998
        },
        {
          "text": "especially",
          "start": 78.92,
          "end": 79.58,
          "confidence": 0.412
        },
        {
          "text": "after",
          "start": 79.58,
          "end": 79.96,
          "confidence": 0.995
        },
        {
          "text": "last",
          "start": 79.96,
          "end": 80.74,
          "confidence": 0.896
        },
        {
          "text": "episode",
          "start": 80.74,
          "end": 81.16,
          "confidence": 0.994
        },
        {
          "text": "was",
          "start": 81.16,
          "end": 81.42,
          "confidence": 0.935
        },
        {
          "text": "like",
          "start": 81.42,
          "end": 81.6,
          "confidence": 0.961
        },
        {
          "text": "a",
          "start": 81.6,
          "end": 81.68,
          "confidence": 0.999
        },
        {
          "text": "lot",
          "start": 81.68,
          "end": 81.8,
          "confidence": 1.0
        },
        {
          "text": "of",
          "start": 81.8,
          "end": 81.98,
          "confidence": 1.0
        },
        {
          "text": "politics",
          "start": 81.98,
          "end": 82.5,
          "confidence": 0.996
        },
        {
          "text": "talk",
          "start": 82.5,
          "end": 82.78,
          "confidence": 0.97
        },
        {
          "text": "and",
          "start": 82.78,
          "end": 83.0,
          "confidence": 0.943
        },
        {
          "text": "I",
          "start": 83.0,
          "end": 83.12,
          "confidence": 0.912
        },
        {
          "text": "was",
          "start": 83.12,
          "end": 83.22,
          "confidence": 0.513
        }
      ]
    },
    {
      "id": 14,
      "seek": 7840,
      "start": 83.22,
      "end": 90.18,
      "text": " very like anxious avoidant of talking about politics. I have been very encouraged",
      "tokens": [
        588,
        411,
        15166,
        5042,
        394,
        295,
        1417,
        466,
        7341,
        13,
        286,
        362,
        668,
        588,
        14658
      ],
      "temperature": 0.0,
      "avg_logprob": -0.16343972590062525,
      "compression_ratio": 1.675531914893617,
      "no_speech_prob": 0.0002010688913287595,
      "confidence": 0.902,
      "words": [
        {
          "text": "very",
          "start": 83.22,
          "end": 83.56,
          "confidence": 0.998
        },
        {
          "text": "like",
          "start": 83.56,
          "end": 83.9,
          "confidence": 0.811
        },
        {
          "text": "anxious",
          "start": 83.9,
          "end": 85.24,
          "confidence": 0.966
        },
        {
          "text": "avoidant",
          "start": 85.24,
          "end": 85.82,
          "confidence": 0.815
        },
        {
          "text": "of",
          "start": 85.82,
          "end": 86.2,
          "confidence": 0.962
        },
        {
          "text": "talking",
          "start": 86.2,
          "end": 88.22,
          "confidence": 0.844
        },
        {
          "text": "about",
          "start": 88.22,
          "end": 88.5,
          "confidence": 0.999
        },
        {
          "text": "politics.",
          "start": 88.5,
          "end": 88.9,
          "confidence": 0.996
        },
        {
          "text": "I",
          "start": 89.16,
          "end": 89.44,
          "confidence": 0.971
        },
        {
          "text": "have",
          "start": 89.44,
          "end": 89.56,
          "confidence": 0.925
        },
        {
          "text": "been",
          "start": 89.56,
          "end": 89.68,
          "confidence": 0.995
        },
        {
          "text": "very",
          "start": 89.68,
          "end": 89.86,
          "confidence": 0.995
        },
        {
          "text": "encouraged",
          "start": 89.86,
          "end": 90.18,
          "confidence": 0.631
        }
      ]
    },
    {
      "id": 15,
      "seek": 7840,
      "start": 90.26,
      "end": 96.7,
      "text": " by the response to that last episode to like not be so anxious about it. I",
      "tokens": [
        538,
        264,
        4134,
        281,
        300,
        1036,
        3500,
        281,
        411,
        406,
        312,
        370,
        15166,
        466,
        309,
        13,
        286
      ],
      "temperature": 0.0,
      "avg_logprob": -0.16343972590062525,
      "compression_ratio": 1.675531914893617,
      "no_speech_prob": 0.0002010688913287595,
      "confidence": 0.977,
      "words": [
        {
          "text": "by",
          "start": 90.26,
          "end": 90.44,
          "confidence": 0.999
        },
        {
          "text": "the",
          "start": 90.44,
          "end": 90.54,
          "confidence": 0.996
        },
        {
          "text": "response",
          "start": 90.54,
          "end": 90.8,
          "confidence": 0.999
        },
        {
          "text": "to",
          "start": 90.8,
          "end": 91.08,
          "confidence": 0.999
        },
        {
          "text": "that",
          "start": 91.08,
          "end": 91.24,
          "confidence": 0.991
        },
        {
          "text": "last",
          "start": 91.24,
          "end": 91.56,
          "confidence": 0.998
        },
        {
          "text": "episode",
          "start": 91.56,
          "end": 91.98,
          "confidence": 0.998
        },
        {
          "text": "to",
          "start": 91.98,
          "end": 92.38,
          "confidence": 0.952
        },
        {
          "text": "like",
          "start": 92.38,
          "end": 93.4,
          "confidence": 0.965
        },
        {
          "text": "not",
          "start": 93.4,
          "end": 93.74,
          "confidence": 0.909
        },
        {
          "text": "be",
          "start": 93.74,
          "end": 93.94,
          "confidence": 0.998
        },
        {
          "text": "so",
          "start": 93.94,
          "end": 94.28,
          "confidence": 0.996
        },
        {
          "text": "anxious",
          "start": 94.28,
          "end": 95.3,
          "confidence": 0.993
        },
        {
          "text": "about",
          "start": 95.3,
          "end": 95.62,
          "confidence": 0.982
        },
        {
          "text": "it.",
          "start": 95.62,
          "end": 95.96,
          "confidence": 0.987
        },
        {
          "text": "I",
          "start": 96.68,
          "end": 96.7,
          "confidence": 0.883
        }
      ]
    },
    {
      "id": 16,
      "seek": 7840,
      "start": 97.64,
      "end": 102.7,
      "text": " don't I still don't know if I'm gonna like start getting full political but I",
      "tokens": [
        500,
        380,
        286,
        920,
        500,
        380,
        458,
        498,
        286,
        478,
        799,
        411,
        722,
        1242,
        1577,
        3905,
        457,
        286
      ],
      "temperature": 0.0,
      "avg_logprob": -0.16343972590062525,
      "compression_ratio": 1.675531914893617,
      "no_speech_prob": 0.0002010688913287595,
      "confidence": 0.925,
      "words": [
        {
          "text": "don't",
          "start": 97.64,
          "end": 97.82,
          "confidence": 0.922
        },
        {
          "text": "I",
          "start": 97.82,
          "end": 97.94,
          "confidence": 0.771
        },
        {
          "text": "still",
          "start": 97.94,
          "end": 98.18,
          "confidence": 0.997
        },
        {
          "text": "don't",
          "start": 98.18,
          "end": 98.44,
          "confidence": 0.996
        },
        {
          "text": "know",
          "start": 98.44,
          "end": 98.6,
          "confidence": 0.999
        },
        {
          "text": "if",
          "start": 98.6,
          "end": 98.78,
          "confidence": 0.999
        },
        {
          "text": "I'm",
          "start": 98.78,
          "end": 98.94,
          "confidence": 0.995
        },
        {
          "text": "gonna",
          "start": 98.94,
          "end": 99.1,
          "confidence": 0.645
        },
        {
          "text": "like",
          "start": 99.1,
          "end": 99.3,
          "confidence": 0.988
        },
        {
          "text": "start",
          "start": 99.3,
          "end": 100.08,
          "confidence": 0.84
        },
        {
          "text": "getting",
          "start": 100.08,
          "end": 100.34,
          "confidence": 0.992
        },
        {
          "text": "full",
          "start": 100.34,
          "end": 100.6,
          "confidence": 0.993
        },
        {
          "text": "political",
          "start": 100.6,
          "end": 101.06,
          "confidence": 0.946
        },
        {
          "text": "but",
          "start": 101.06,
          "end": 102.52,
          "confidence": 0.819
        },
        {
          "text": "I",
          "start": 102.52,
          "end": 102.7,
          "confidence": 0.941
        }
      ]
    },
    {
      "id": 17,
      "seek": 10264,
      "start": 102.7,
      "end": 110.44,
      "text": " will try not to like avoid it in the game because of my personal issues with",
      "tokens": [
        486,
        853,
        406,
        281,
        411,
        5042,
        309,
        294,
        264,
        1216,
        570,
        295,
        452,
        2973,
        2663,
        365
      ],
      "temperature": 0.0,
      "avg_logprob": -0.1462929940992786,
      "compression_ratio": 1.6964285714285714,
      "no_speech_prob": 2.8008562367176637e-05,
      "confidence": 0.974,
      "words": [
        {
          "text": "will",
          "start": 102.7,
          "end": 102.94,
          "confidence": 0.996
        },
        {
          "text": "try",
          "start": 102.94,
          "end": 103.24,
          "confidence": 0.999
        },
        {
          "text": "not",
          "start": 103.24,
          "end": 103.44,
          "confidence": 0.998
        },
        {
          "text": "to",
          "start": 103.44,
          "end": 103.64,
          "confidence": 0.998
        },
        {
          "text": "like",
          "start": 103.64,
          "end": 103.88,
          "confidence": 0.981
        },
        {
          "text": "avoid",
          "start": 103.88,
          "end": 104.22,
          "confidence": 0.998
        },
        {
          "text": "it",
          "start": 104.22,
          "end": 104.42,
          "confidence": 0.992
        },
        {
          "text": "in",
          "start": 104.42,
          "end": 104.62,
          "confidence": 0.996
        },
        {
          "text": "the",
          "start": 104.62,
          "end": 104.76,
          "confidence": 0.998
        },
        {
          "text": "game",
          "start": 104.76,
          "end": 105.14,
          "confidence": 1.0
        },
        {
          "text": "because",
          "start": 105.14,
          "end": 106.0,
          "confidence": 0.963
        },
        {
          "text": "of",
          "start": 106.0,
          "end": 106.24,
          "confidence": 0.999
        },
        {
          "text": "my",
          "start": 106.24,
          "end": 106.46,
          "confidence": 1.0
        },
        {
          "text": "personal",
          "start": 106.46,
          "end": 107.32,
          "confidence": 0.997
        },
        {
          "text": "issues",
          "start": 107.32,
          "end": 109.8,
          "confidence": 0.857
        },
        {
          "text": "with",
          "start": 109.8,
          "end": 110.44,
          "confidence": 0.838
        }
      ]
    },
    {
      "id": 18,
      "seek": 10264,
      "start": 110.44,
      "end": 115.28,
      "text": " with getting political. I'll just say that I I won't let it divert the game",
      "tokens": [
        365,
        1242,
        3905,
        13,
        286,
        603,
        445,
        584,
        300,
        286,
        286,
        1582,
        380,
        718,
        309,
        23781,
        264,
        1216
      ],
      "temperature": 0.0,
      "avg_logprob": -0.1462929940992786,
      "compression_ratio": 1.6964285714285714,
      "no_speech_prob": 2.8008562367176637e-05,
      "confidence": 0.908,
      "words": [
        {
          "text": "with",
          "start": 110.44,
          "end": 110.9,
          "confidence": 0.762
        },
        {
          "text": "getting",
          "start": 110.9,
          "end": 111.26,
          "confidence": 0.996
        },
        {
          "text": "political.",
          "start": 111.26,
          "end": 111.8,
          "confidence": 0.999
        },
        {
          "text": "I'll",
          "start": 112.56,
          "end": 112.72,
          "confidence": 0.997
        },
        {
          "text": "just",
          "start": 112.72,
          "end": 112.84,
          "confidence": 1.0
        },
        {
          "text": "say",
          "start": 112.84,
          "end": 113.04,
          "confidence": 0.999
        },
        {
          "text": "that",
          "start": 113.04,
          "end": 113.3,
          "confidence": 0.999
        },
        {
          "text": "I",
          "start": 113.3,
          "end": 113.78,
          "confidence": 0.67
        },
        {
          "text": "I",
          "start": 113.78,
          "end": 114.12,
          "confidence": 0.465
        },
        {
          "text": "won't",
          "start": 114.12,
          "end": 114.28,
          "confidence": 0.987
        },
        {
          "text": "let",
          "start": 114.28,
          "end": 114.4,
          "confidence": 0.997
        },
        {
          "text": "it",
          "start": 114.4,
          "end": 114.52,
          "confidence": 0.997
        },
        {
          "text": "divert",
          "start": 114.52,
          "end": 114.84,
          "confidence": 0.946
        },
        {
          "text": "the",
          "start": 114.84,
          "end": 115.1,
          "confidence": 0.99
        },
        {
          "text": "game",
          "start": 115.1,
          "end": 115.28,
          "confidence": 0.913
        }
      ]
    },
    {
      "id": 19,
      "seek": 10264,
      "start": 115.52,
      "end": 118.54,
      "text": " because at the end of the day I want to talk about like mental health and",
      "tokens": [
        570,
        412,
        264,
        917,
        295,
        264,
        786,
        286,
        528,
        281,
        751,
        466,
        411,
        4973,
        1585,
        293
      ],
      "temperature": 0.0,
      "avg_logprob": -0.1462929940992786,
      "compression_ratio": 1.6964285714285714,
      "no_speech_prob": 2.8008562367176637e-05,
      "confidence": 0.988,
      "words": [
        {
          "text": "because",
          "start": 115.52,
          "end": 115.74,
          "confidence": 0.997
        },
        {
          "text": "at",
          "start": 115.74,
          "end": 115.9,
          "confidence": 0.989
        },
        {
          "text": "the",
          "start": 115.9,
          "end": 116.0,
          "confidence": 1.0
        },
        {
          "text": "end",
          "start": 116.0,
          "end": 116.1,
          "confidence": 0.999
        },
        {
          "text": "of",
          "start": 116.1,
          "end": 116.18,
          "confidence": 1.0
        },
        {
          "text": "the",
          "start": 116.18,
          "end": 116.26,
          "confidence": 1.0
        },
        {
          "text": "day",
          "start": 116.26,
          "end": 116.44,
          "confidence": 1.0
        },
        {
          "text": "I",
          "start": 116.44,
          "end": 116.6,
          "confidence": 0.965
        },
        {
          "text": "want",
          "start": 116.6,
          "end": 116.78,
          "confidence": 0.974
        },
        {
          "text": "to",
          "start": 116.78,
          "end": 116.88,
          "confidence": 1.0
        },
        {
          "text": "talk",
          "start": 116.88,
          "end": 117.08,
          "confidence": 1.0
        },
        {
          "text": "about",
          "start": 117.08,
          "end": 117.36,
          "confidence": 1.0
        },
        {
          "text": "like",
          "start": 117.36,
          "end": 117.66,
          "confidence": 0.995
        },
        {
          "text": "mental",
          "start": 117.66,
          "end": 118.0,
          "confidence": 0.987
        },
        {
          "text": "health",
          "start": 118.0,
          "end": 118.4,
          "confidence": 0.998
        },
        {
          "text": "and",
          "start": 118.4,
          "end": 118.54,
          "confidence": 0.916
        }
      ]
    },
    {
      "id": 20,
      "seek": 10264,
      "start": 119.02,
      "end": 124.52,
      "text": " there's probably some interesting avenues in the narrative of the game that",
      "tokens": [
        456,
        311,
        1391,
        512,
        1880,
        43039,
        294,
        264,
        9977,
        295,
        264,
        1216,
        300
      ],
      "temperature": 0.0,
      "avg_logprob": -0.1462929940992786,
      "compression_ratio": 1.6964285714285714,
      "no_speech_prob": 2.8008562367176637e-05,
      "confidence": 0.956,
      "words": [
        {
          "text": "there's",
          "start": 119.02,
          "end": 119.3,
          "confidence": 0.997
        },
        {
          "text": "probably",
          "start": 119.3,
          "end": 119.46,
          "confidence": 0.994
        },
        {
          "text": "some",
          "start": 119.46,
          "end": 119.66,
          "confidence": 1.0
        },
        {
          "text": "interesting",
          "start": 119.66,
          "end": 120.08,
          "confidence": 0.999
        },
        {
          "text": "avenues",
          "start": 120.08,
          "end": 120.64,
          "confidence": 0.992
        },
        {
          "text": "in",
          "start": 120.64,
          "end": 122.82,
          "confidence": 0.96
        },
        {
          "text": "the",
          "start": 122.82,
          "end": 123.28,
          "confidence": 0.995
        },
        {
          "text": "narrative",
          "start": 123.28,
          "end": 123.8,
          "confidence": 0.694
        },
        {
          "text": "of",
          "start": 123.8,
          "end": 124.04,
          "confidence": 0.997
        },
        {
          "text": "the",
          "start": 124.04,
          "end": 124.16,
          "confidence": 0.994
        },
        {
          "text": "game",
          "start": 124.16,
          "end": 124.34,
          "confidence": 0.964
        },
        {
          "text": "that",
          "start": 124.34,
          "end": 124.52,
          "confidence": 0.901
        }
      ]
    },
    {
      "id": 21,
      "seek": 10264,
      "start": 124.52,
      "end": 129.54,
      "text": " will miss out on if I just totally ignore it. However I will say this game is",
      "tokens": [
        486,
        1713,
        484,
        322,
        498,
        286,
        445,
        3879,
        11200,
        309,
        13,
        2908,
        286,
        486,
        584,
        341,
        1216,
        307
      ],
      "temperature": 0.0,
      "avg_logprob": -0.1462929940992786,
      "compression_ratio": 1.6964285714285714,
      "no_speech_prob": 2.8008562367176637e-05,
      "confidence": 0.952,
      "words": [
        {
          "text": "will",
          "start": 124.52,
          "end": 124.76,
          "confidence": 0.772
        },
        {
          "text": "miss",
          "start": 124.76,
          "end": 124.94,
          "confidence": 0.841
        },
        {
          "text": "out",
          "start": 124.94,
          "end": 125.12,
          "confidence": 0.998
        },
        {
          "text": "on",
          "start": 125.12,
          "end": 125.28,
          "confidence": 0.997
        },
        {
          "text": "if",
          "start": 125.28,
          "end": 125.42,
          "confidence": 0.979
        },
        {
          "text": "I",
          "start": 125.42,
          "end": 125.52,
          "confidence": 0.997
        },
        {
          "text": "just",
          "start": 125.52,
          "end": 125.68,
          "confidence": 0.999
        },
        {
          "text": "totally",
          "start": 125.68,
          "end": 126.08,
          "confidence": 0.998
        },
        {
          "text": "ignore",
          "start": 126.08,
          "end": 126.44,
          "confidence": 0.997
        },
        {
          "text": "it.",
          "start": 126.44,
          "end": 126.68,
          "confidence": 0.997
        },
        {
          "text": "However",
          "start": 127.24,
          "end": 127.46,
          "confidence": 0.947
        },
        {
          "text": "I",
          "start": 127.46,
          "end": 127.8,
          "confidence": 0.804
        },
        {
          "text": "will",
          "start": 127.8,
          "end": 127.92,
          "confidence": 0.997
        },
        {
          "text": "say",
          "start": 127.92,
          "end": 128.16,
          "confidence": 0.996
        },
        {
          "text": "this",
          "start": 128.16,
          "end": 128.36,
          "confidence": 0.979
        },
        {
          "text": "game",
          "start": 128.36,
          "end": 128.62,
          "confidence": 0.974
        },
        {
          "text": "is",
          "start": 128.62,
          "end": 129.54,
          "confidence": 0.957
        }
      ]
    },
    {
      "id": 22,
      "seek": 13168,
      "start": 132.16,
      "end": 138.66,
      "text": " so wonderfully designed that it you have a main character who has a real back",
      "tokens": [
        370,
        38917,
        4761,
        300,
        309,
        291,
        362,
        257,
        2135,
        2517,
        567,
        575,
        257,
        957,
        646
      ],
      "temperature": 0.0,
      "avg_logprob": -0.1554324467976888,
      "compression_ratio": 1.6946902654867257,
      "no_speech_prob": 0.00019003043416887522,
      "confidence": 0.912,
      "words": [
        {
          "text": "so",
          "start": 132.16,
          "end": 133.26,
          "confidence": 0.97
        },
        {
          "text": "wonderfully",
          "start": 133.26,
          "end": 133.72,
          "confidence": 0.998
        },
        {
          "text": "designed",
          "start": 133.72,
          "end": 134.34,
          "confidence": 0.994
        },
        {
          "text": "that",
          "start": 134.34,
          "end": 134.68,
          "confidence": 0.969
        },
        {
          "text": "it",
          "start": 134.68,
          "end": 134.96,
          "confidence": 0.624
        },
        {
          "text": "you",
          "start": 134.96,
          "end": 136.4,
          "confidence": 0.803
        },
        {
          "text": "have",
          "start": 136.4,
          "end": 136.52,
          "confidence": 0.998
        },
        {
          "text": "a",
          "start": 136.52,
          "end": 136.64,
          "confidence": 0.99
        },
        {
          "text": "main",
          "start": 136.64,
          "end": 136.92,
          "confidence": 0.986
        },
        {
          "text": "character",
          "start": 136.92,
          "end": 137.38,
          "confidence": 0.994
        },
        {
          "text": "who",
          "start": 137.38,
          "end": 137.64,
          "confidence": 0.993
        },
        {
          "text": "has",
          "start": 137.64,
          "end": 137.86,
          "confidence": 0.997
        },
        {
          "text": "a",
          "start": 137.86,
          "end": 138.14,
          "confidence": 0.982
        },
        {
          "text": "real",
          "start": 138.14,
          "end": 138.42,
          "confidence": 0.901
        },
        {
          "text": "back",
          "start": 138.42,
          "end": 138.66,
          "confidence": 0.637
        }
      ]
    },
    {
      "id": 23,
      "seek": 13168,
      "start": 138.68,
      "end": 142.15,
      "text": " story. He's not like a blank slate like I thought that he was gonna be from",
      "tokens": [
        1657,
        13,
        634,
        311,
        406,
        411,
        257,
        8247,
        39118,
        411,
        286,
        1194,
        300,
        415,
        390,
        799,
        312,
        490
      ],
      "temperature": 0.0,
      "avg_logprob": -0.1554324467976888,
      "compression_ratio": 1.6946902654867257,
      "no_speech_prob": 0.00019003043416887522,
      "confidence": 0.916,
      "words": [
        {
          "text": "story.",
          "start": 138.68,
          "end": 139.0,
          "confidence": 0.744
        },
        {
          "text": "He's",
          "start": 139.0,
          "end": 139.2,
          "confidence": 0.989
        },
        {
          "text": "not",
          "start": 139.2,
          "end": 139.3,
          "confidence": 0.999
        },
        {
          "text": "like",
          "start": 139.3,
          "end": 139.44,
          "confidence": 0.998
        },
        {
          "text": "a",
          "start": 139.44,
          "end": 139.54,
          "confidence": 0.983
        },
        {
          "text": "blank",
          "start": 139.54,
          "end": 139.74,
          "confidence": 0.564
        },
        {
          "text": "slate",
          "start": 139.74,
          "end": 140.08,
          "confidence": 0.985
        },
        {
          "text": "like",
          "start": 140.08,
          "end": 140.28,
          "confidence": 0.894
        },
        {
          "text": "I",
          "start": 140.28,
          "end": 140.44,
          "confidence": 0.991
        },
        {
          "text": "thought",
          "start": 140.44,
          "end": 140.72,
          "confidence": 0.997
        },
        {
          "text": "that",
          "start": 140.72,
          "end": 140.96,
          "confidence": 0.988
        },
        {
          "text": "he",
          "start": 140.96,
          "end": 141.1,
          "confidence": 0.992
        },
        {
          "text": "was",
          "start": 141.1,
          "end": 141.32,
          "confidence": 0.996
        },
        {
          "text": "gonna",
          "start": 141.32,
          "end": 141.78,
          "confidence": 0.746
        },
        {
          "text": "be",
          "start": 141.78,
          "end": 141.96,
          "confidence": 0.995
        },
        {
          "text": "from",
          "start": 141.96,
          "end": 142.15,
          "confidence": 0.881
        }
      ]
    },
    {
      "id": 24,
      "seek": 13168,
      "start": 142.15,
      "end": 146.82,
      "text": " the beginning. He has his own back story and at the same time it allows you to",
      "tokens": [
        264,
        2863,
        13,
        634,
        575,
        702,
        1065,
        646,
        1657,
        293,
        412,
        264,
        912,
        565,
        309,
        4045,
        291,
        281
      ],
      "temperature": 0.0,
      "avg_logprob": -0.1554324467976888,
      "compression_ratio": 1.6946902654867257,
      "no_speech_prob": 0.00019003043416887522,
      "confidence": 0.954,
      "words": [
        {
          "text": "the",
          "start": 142.15,
          "end": 142.26,
          "confidence": 0.997
        },
        {
          "text": "beginning.",
          "start": 142.26,
          "end": 142.54,
          "confidence": 0.999
        },
        {
          "text": "He",
          "start": 143.2,
          "end": 143.3,
          "confidence": 0.865
        },
        {
          "text": "has",
          "start": 143.3,
          "end": 143.42,
          "confidence": 0.954
        },
        {
          "text": "his",
          "start": 143.42,
          "end": 143.5,
          "confidence": 0.945
        },
        {
          "text": "own",
          "start": 143.5,
          "end": 143.62,
          "confidence": 0.985
        },
        {
          "text": "back",
          "start": 143.62,
          "end": 143.8,
          "confidence": 0.81
        },
        {
          "text": "story",
          "start": 143.8,
          "end": 144.16,
          "confidence": 0.984
        },
        {
          "text": "and",
          "start": 144.16,
          "end": 144.38,
          "confidence": 0.939
        },
        {
          "text": "at",
          "start": 144.38,
          "end": 144.5,
          "confidence": 0.998
        },
        {
          "text": "the",
          "start": 144.5,
          "end": 144.58,
          "confidence": 0.997
        },
        {
          "text": "same",
          "start": 144.58,
          "end": 144.78,
          "confidence": 0.967
        },
        {
          "text": "time",
          "start": 144.78,
          "end": 145.14,
          "confidence": 0.99
        },
        {
          "text": "it",
          "start": 145.14,
          "end": 145.76,
          "confidence": 0.957
        },
        {
          "text": "allows",
          "start": 145.76,
          "end": 146.04,
          "confidence": 0.987
        },
        {
          "text": "you",
          "start": 146.04,
          "end": 146.46,
          "confidence": 0.966
        },
        {
          "text": "to",
          "start": 146.46,
          "end": 146.82,
          "confidence": 0.907
        }
      ]
    },
    {
      "id": 25,
      "seek": 13168,
      "start": 148.78,
      "end": 155.01,
      "text": " have your own beliefs and and to and the character will like have the same",
      "tokens": [
        362,
        428,
        1065,
        13585,
        293,
        293,
        281,
        293,
        264,
        2517,
        486,
        411,
        362,
        264,
        912
      ],
      "temperature": 0.0,
      "avg_logprob": -0.1554324467976888,
      "compression_ratio": 1.6946902654867257,
      "no_speech_prob": 0.00019003043416887522,
      "confidence": 0.9,
      "words": [
        {
          "text": "have",
          "start": 148.78,
          "end": 149.1,
          "confidence": 0.997
        },
        {
          "text": "your",
          "start": 149.1,
          "end": 149.28,
          "confidence": 0.999
        },
        {
          "text": "own",
          "start": 149.28,
          "end": 149.44,
          "confidence": 1.0
        },
        {
          "text": "beliefs",
          "start": 149.44,
          "end": 149.86,
          "confidence": 1.0
        },
        {
          "text": "and",
          "start": 149.86,
          "end": 152.24,
          "confidence": 0.872
        },
        {
          "text": "and",
          "start": 152.24,
          "end": 152.44,
          "confidence": 0.577
        },
        {
          "text": "to",
          "start": 152.44,
          "end": 153.0,
          "confidence": 0.499
        },
        {
          "text": "and",
          "start": 153.0,
          "end": 153.34,
          "confidence": 0.964
        },
        {
          "text": "the",
          "start": 153.34,
          "end": 153.46,
          "confidence": 0.992
        },
        {
          "text": "character",
          "start": 153.46,
          "end": 153.8,
          "confidence": 0.986
        },
        {
          "text": "will",
          "start": 153.8,
          "end": 154.12,
          "confidence": 0.995
        },
        {
          "text": "like",
          "start": 154.12,
          "end": 154.38,
          "confidence": 0.984
        },
        {
          "text": "have",
          "start": 154.38,
          "end": 154.68,
          "confidence": 0.985
        },
        {
          "text": "the",
          "start": 154.68,
          "end": 154.84,
          "confidence": 0.993
        },
        {
          "text": "same",
          "start": 154.84,
          "end": 155.01,
          "confidence": 0.913
        }
      ]
    },
    {
      "id": 26,
      "seek": 13168,
      "start": 155.01,
      "end": 160.94,
      "text": " behavioral patterns. Like genuinely imagine if like literally Brady was the",
      "tokens": [
        19124,
        8294,
        13,
        1743,
        17839,
        3811,
        498,
        411,
        3736,
        31773,
        390,
        264
      ],
      "temperature": 0.0,
      "avg_logprob": -0.1554324467976888,
      "compression_ratio": 1.6946902654867257,
      "no_speech_prob": 0.00019003043416887522,
      "confidence": 0.91,
      "words": [
        {
          "text": "behavioral",
          "start": 155.01,
          "end": 155.46,
          "confidence": 0.538
        },
        {
          "text": "patterns.",
          "start": 155.46,
          "end": 156.12,
          "confidence": 0.996
        },
        {
          "text": "Like",
          "start": 157.52,
          "end": 157.7,
          "confidence": 0.947
        },
        {
          "text": "genuinely",
          "start": 157.7,
          "end": 158.1,
          "confidence": 0.986
        },
        {
          "text": "imagine",
          "start": 158.1,
          "end": 158.6,
          "confidence": 0.971
        },
        {
          "text": "if",
          "start": 158.6,
          "end": 158.9,
          "confidence": 0.991
        },
        {
          "text": "like",
          "start": 158.9,
          "end": 159.04,
          "confidence": 0.987
        },
        {
          "text": "literally",
          "start": 159.04,
          "end": 159.44,
          "confidence": 0.971
        },
        {
          "text": "Brady",
          "start": 159.44,
          "end": 159.9,
          "confidence": 0.914
        },
        {
          "text": "was",
          "start": 159.9,
          "end": 160.7,
          "confidence": 0.941
        },
        {
          "text": "the",
          "start": 160.7,
          "end": 160.94,
          "confidence": 0.892
        }
      ]
    },
    {
      "id": 27,
      "seek": 16096,
      "start": 160.96,
      "end": 166.84,
      "text": " detective. Imagine it what you know about me so far. How I would go about",
      "tokens": [
        25571,
        13,
        11739,
        309,
        437,
        291,
        458,
        466,
        385,
        370,
        1400,
        13,
        1012,
        286,
        576,
        352,
        466
      ],
      "temperature": 0.0,
      "avg_logprob": -0.2489168239089678,
      "compression_ratio": 1.4755244755244756,
      "no_speech_prob": 2.8958593247807585e-05,
      "confidence": 0.911,
      "words": [
        {
          "text": "detective.",
          "start": 160.96,
          "end": 161.4,
          "confidence": 0.981
        },
        {
          "text": "Imagine",
          "start": 162.14,
          "end": 162.52,
          "confidence": 0.967
        },
        {
          "text": "it",
          "start": 162.52,
          "end": 163.02,
          "confidence": 0.766
        },
        {
          "text": "what",
          "start": 163.02,
          "end": 163.7,
          "confidence": 0.422
        },
        {
          "text": "you",
          "start": 163.7,
          "end": 163.84,
          "confidence": 0.965
        },
        {
          "text": "know",
          "start": 163.84,
          "end": 164.02,
          "confidence": 0.998
        },
        {
          "text": "about",
          "start": 164.02,
          "end": 164.24,
          "confidence": 0.997
        },
        {
          "text": "me",
          "start": 164.24,
          "end": 164.44,
          "confidence": 0.995
        },
        {
          "text": "so",
          "start": 164.44,
          "end": 164.64,
          "confidence": 0.984
        },
        {
          "text": "far.",
          "start": 164.64,
          "end": 164.98,
          "confidence": 0.992
        },
        {
          "text": "How",
          "start": 165.76,
          "end": 165.98,
          "confidence": 0.942
        },
        {
          "text": "I",
          "start": 165.98,
          "end": 166.28,
          "confidence": 0.983
        },
        {
          "text": "would",
          "start": 166.28,
          "end": 166.46,
          "confidence": 0.995
        },
        {
          "text": "go",
          "start": 166.46,
          "end": 166.62,
          "confidence": 0.995
        },
        {
          "text": "about",
          "start": 166.62,
          "end": 166.84,
          "confidence": 0.943
        }
      ]
    },
    {
      "id": 28,
      "seek": 16096,
      "start": 166.84,
      "end": 170.92,
      "text": " solving a murder would be exactly like you've seen it like I would spend",
      "tokens": [
        12606,
        257,
        6568,
        576,
        312,
        2293,
        411,
        291,
        600,
        1612,
        309,
        411,
        286,
        576,
        3496
      ],
      "temperature": 0.0,
      "avg_logprob": -0.2489168239089678,
      "compression_ratio": 1.4755244755244756,
      "no_speech_prob": 2.8958593247807585e-05,
      "confidence": 0.966,
      "words": [
        {
          "text": "solving",
          "start": 166.84,
          "end": 167.2,
          "confidence": 0.99
        },
        {
          "text": "a",
          "start": 167.2,
          "end": 167.36,
          "confidence": 0.998
        },
        {
          "text": "murder",
          "start": 167.36,
          "end": 167.62,
          "confidence": 0.975
        },
        {
          "text": "would",
          "start": 167.62,
          "end": 168.24,
          "confidence": 0.987
        },
        {
          "text": "be",
          "start": 168.24,
          "end": 168.42,
          "confidence": 0.999
        },
        {
          "text": "exactly",
          "start": 168.42,
          "end": 169.02,
          "confidence": 0.995
        },
        {
          "text": "like",
          "start": 169.02,
          "end": 169.42,
          "confidence": 0.981
        },
        {
          "text": "you've",
          "start": 169.42,
          "end": 169.68,
          "confidence": 0.997
        },
        {
          "text": "seen",
          "start": 169.68,
          "end": 169.84,
          "confidence": 0.998
        },
        {
          "text": "it",
          "start": 169.84,
          "end": 170.02,
          "confidence": 0.99
        },
        {
          "text": "like",
          "start": 170.02,
          "end": 170.2,
          "confidence": 0.678
        },
        {
          "text": "I",
          "start": 170.2,
          "end": 170.42,
          "confidence": 0.984
        },
        {
          "text": "would",
          "start": 170.42,
          "end": 170.58,
          "confidence": 0.998
        },
        {
          "text": "spend",
          "start": 170.58,
          "end": 170.92,
          "confidence": 0.983
        }
      ]
    },
    {
      "id": 29,
      "seek": 17188,
      "start": 171.88,
      "end": 179.2,
      "text": " crazy amounts of time on things that you just wouldn't like you.",
      "tokens": [
        50364,
        3219,
        11663,
        295,
        565,
        322,
        721,
        300,
        291,
        445,
        2759,
        380,
        411,
        291,
        13,
        51862
      ],
      "temperature": 0.0,
      "avg_logprob": -0.3451693198260139,
      "compression_ratio": 0.9552238805970149,
      "no_speech_prob": 3.88644402846694e-05,
      "confidence": 0.922,
      "words": [
        {
          "text": "crazy",
          "start": 171.88,
          "end": 172.68,
          "confidence": 0.978
        },
        {
          "text": "amounts",
          "start": 172.68,
          "end": 173.02,
          "confidence": 0.992
        },
        {
          "text": "of",
          "start": 173.02,
          "end": 173.26,
          "confidence": 1.0
        },
        {
          "text": "time",
          "start": 173.26,
          "end": 173.6,
          "confidence": 0.999
        },
        {
          "text": "on",
          "start": 173.6,
          "end": 174.86,
          "confidence": 0.981
        },
        {
          "text": "things",
          "start": 174.86,
          "end": 175.18,
          "confidence": 0.999
        },
        {
          "text": "that",
          "start": 175.18,
          "end": 175.58,
          "confidence": 0.997
        },
        {
          "text": "you",
          "start": 175.58,
          "end": 176.46,
          "confidence": 0.984
        },
        {
          "text": "just",
          "start": 176.46,
          "end": 176.66,
          "confidence": 0.999
        },
        {
          "text": "wouldn't",
          "start": 176.66,
          "end": 177.12,
          "confidence": 0.998
        },
        {
          "text": "like",
          "start": 177.12,
          "end": 177.72,
          "confidence": 0.978
        },
        {
          "text": "you.",
          "start": 177.72,
          "end": 179.2,
          "confidence": 0.386
        }
      ]
    }
  ],
  "language": "en"
}